{
 "city": "半田市",
 "asof": "2026-06-18",
 "target": "2026年8月入園分（令和8年8月入園募集時点）",
 "source": "https://www.city.handa.lg.jp/kosodate/hoikuen-youchien/1002100/1010914.html",
 "legend": "数字は受入可能数（令和8年6月18日現在）。×は定員を満たしていることを示す。空欄はその年齢の受け入れを行っていないことを示す",
 "ages": [
  "0歳児",
  "1歳児",
  "2歳児",
  "3歳児",
  "4歳児",
  "5歳児"
 ],
 "items": {
  "岩滑こども園 （長時間利用）": {
   "aki": [
    "×",
    "×",
    "×",
    "1",
    "8",
    "8"
   ]
  },
  "亀崎幼稚園 （長時間利用）": {
   "aki": [
    "",
    "",
    "",
    "13",
    "5",
    "×"
   ]
  },
  "板山こども園 （長時間利用）": {
   "aki": [
    "×",
    "×",
    "×",
    "×",
    "9",
    "×"
   ]
  },
  "葵保育園": {
   "aki": [
    "",
    "×",
    "×",
    "11",
    "24",
    "25"
   ]
  },
  "有脇保育園": {
   "aki": [
    "",
    "×",
    "2",
    "10",
    "16",
    "14"
   ]
  },
  "平地保育園": {
   "aki": [
    "×",
    "×",
    "×",
    "7",
    "26",
    "16"
   ]
  },
  "乙川保育園": {
   "aki": [
    "×",
    "×",
    "×",
    "8",
    "15",
    "10"
   ]
  },
  "白山保育園": {
   "aki": [
    "",
    "×",
    "5",
    "8",
    "20",
    "13"
   ]
  },
  "東保育園": {
   "aki": [
    "2",
    "×",
    "3",
    "1",
    "27",
    "2"
   ]
  },
  "修農保育園": {
   "aki": [
    "",
    "×",
    "×",
    "10",
    "19",
    "16"
   ]
  },
  "横川保育園": {
   "aki": [
    "",
    "×",
    "4",
    "×",
    "20",
    "19"
   ]
  },
  "協和保育園": {
   "aki": [
    "1",
    "×",
    "2",
    "4",
    "18",
    "11"
   ]
  },
  "岩滑北保育園": {
   "aki": [
    "",
    "×",
    "3",
    "7",
    "10",
    "14"
   ]
  },
  "清城保育園": {
   "aki": [
    "×",
    "×",
    "×",
    "11",
    "9",
    "29"
   ]
  },
  "半田同胞園保育所": {
   "aki": [
    "1",
    "×",
    "×",
    "×",
    "17",
    "14"
   ]
  },
  "にじいろ保育園花園": {
   "aki": [
    "2",
    "×",
    "×",
    "11",
    "7",
    "5"
   ]
  },
  "住吉こども園": {
   "aki": [
    "×",
    "×",
    "2",
    "2",
    "2",
    "×"
   ]
  },
  "のぞみが丘保育園": {
   "aki": [
    "×",
    "×",
    "×",
    "",
    "",
    ""
   ]
  },
  "みらい保育園": {
   "aki": [
    "",
    "",
    "",
    "×",
    "×",
    "×"
   ]
  },
  "あさひ保育園": {
   "aki": [
    "×",
    "×",
    "1",
    "",
    "",
    ""
   ]
  },
  "アイグラン保育園高根": {
   "aki": [
    "×",
    "×",
    "×",
    "2",
    "1",
    "×"
   ]
  },
  "花・はなベビーハウス": {
   "aki": [
    "5",
    "×",
    "1",
    "",
    "",
    ""
   ]
  },
  "おひさま保育園": {
   "aki": [
    "3",
    "×",
    "1",
    "",
    "",
    ""
   ]
  },
  "わかば保育園": {
   "aki": [
    "1",
    "×",
    "1",
    "",
    "",
    ""
   ]
  },
  "くれよん保育園": {
   "aki": [
    "×",
    "×",
    "×",
    "",
    "",
    ""
   ]
  },
  "めいてつ保育ステーション 知多半田駅ぽっぽ園": {
   "aki": [
    "1",
    "×",
    "1",
    "",
    "",
    ""
   ]
  },
  "さつき保育園": {
   "aki": [
    "×",
    "×",
    "×",
    "",
    "",
    ""
   ]
  }
 }
}