{
 "city": "名古屋市熱田区",
 "asof": "2026-07-01",
 "target": "2026年8月入園分（募集人数）",
 "source": "https://kodomokosodate.city.nagoya.jp/firstuse/boshuwaku.html",
 "legend": "数値=クラス年齢ごとの募集人数。「-」=受入可能年齢でないクラス。「←」=左隣クラスと合わせて募集。受入可能月齢は各施設のnote参照",
 "ages": [
  "産明け",
  "6ヶ月以上",
  "1歳",
  "2歳",
  "3歳",
  "4歳",
  "5歳"
 ],
 "items": {
  "高蔵保育園": {
   "aki": [
    "1",
    "3",
    "0",
    "0",
    "4",
    "11",
    "12"
   ],
   "note": "産休あけ～5歳"
  },
  "宮西保育園": {
   "aki": [
    "-",
    "0",
    "0",
    "3",
    "0",
    "3",
    "4"
   ],
   "note": "6ヶ月～5歳"
  },
  "神宮東保育園": {
   "aki": [
    "-",
    "0",
    "0",
    "1",
    "1",
    "4",
    "3"
   ],
   "note": "6ヶ月～5歳"
  },
  "泉坊保育園": {
   "aki": [
    "1",
    "←",
    "0",
    "1",
    "1",
    "1",
    "0"
   ],
   "note": "産休あけ～5歳"
  },
  "のぎく保育園": {
   "aki": [
    "0",
    "←",
    "0",
    "0",
    "0",
    "0",
    "0"
   ],
   "note": "産休あけ～5歳"
  },
  "一番町保育園": {
   "aki": [
    "-",
    "0",
    "0",
    "0",
    "0",
    "0",
    "0"
   ],
   "note": "6ヶ月～5歳"
  },
  "千年保育園": {
   "aki": [
    "-",
    "0",
    "0",
    "3",
    "2",
    "0",
    "0"
   ],
   "note": "6ヶ月～5歳"
  },
  "金山保育園": {
   "aki": [
    "0",
    "←",
    "0",
    "1",
    "0",
    "0",
    "0"
   ],
   "note": "産休あけ～5歳"
  },
  "船方保育園": {
   "aki": [
    "-",
    "1",
    "0",
    "1",
    "1",
    "0",
    "0"
   ],
   "note": "6ヶ月～5歳"
  },
  "花表こばと保育園": {
   "aki": [
    "0",
    "←",
    "0",
    "0",
    "0",
    "0",
    "0"
   ],
   "note": "産休あけ～5歳"
  },
  "明野保育園": {
   "aki": [
    "0",
    "←",
    "1",
    "0",
    "0",
    "0",
    "0"
   ],
   "note": "産休あけ～5歳"
  },
  "認定こども園日比野保育園": {
   "aki": [
    "0",
    "0",
    "0",
    "0",
    "0",
    "0",
    "0"
   ],
   "note": "5ヶ月～5歳"
  },
  "認定こども園日比野保育園（分園）": {
   "aki": [
    "0",
    "0",
    "0",
    "-",
    "-",
    "-",
    "-"
   ],
   "note": "5ヶ月～1歳"
  },
  "認定こども園高蔵幼児園": {
   "aki": [
    "-",
    "0",
    "0",
    "0",
    "0",
    "0",
    "0"
   ],
   "note": "10ヶ月～5歳"
  },
  "小規模保育事業ソラーナひびの": {
   "aki": [
    "-",
    "0",
    "0",
    "0",
    "-",
    "-",
    "-"
   ],
   "note": "産休あけ～2歳"
  },
  "スクルドエンジェル保育室しろとり園": {
   "aki": [
    "3",
    "←",
    "3",
    "2",
    "-",
    "-",
    "-"
   ],
   "note": "産休あけ～2歳"
  },
  "チャイルドほーむ熱田園": {
   "aki": [
    "0",
    "←",
    "0",
    "0",
    "-",
    "-",
    "-"
   ],
   "note": "産休あけ～2歳"
  },
  "イオンモール熱田保育室": {
   "aki": [
    "1",
    "←",
    "←",
    "←",
    "-",
    "-",
    "-"
   ],
   "note": "産休あけ～2歳"
  },
  "ぶれあ保育室大宝": {
   "aki": [
    "0",
    "←",
    "1",
    "0",
    "-",
    "-",
    "-"
   ],
   "note": "産休あけ～2歳"
  },
  "ぶれあ保育室高蔵": {
   "aki": [
    "0",
    "←",
    "0",
    "0",
    "-",
    "-",
    "-"
   ],
   "note": "産休あけ～2歳"
  },
  "乳児保育六番町園": {
   "aki": [
    "2",
    "←",
    "3",
    "2",
    "-",
    "-",
    "-"
   ],
   "note": "産休あけ～2歳"
  },
  "みんなのみらい幡野園": {
   "aki": [
    "-",
    "2",
    "3",
    "0",
    "-",
    "-",
    "-"
   ],
   "note": "6ヶ月～2歳"
  },
  "あつたこどものいえ": {
   "aki": [
    "0",
    "←",
    "0",
    "0",
    "-",
    "-",
    "-"
   ],
   "note": "産休あけ～2歳"
  },
  "託児所ぷれこ": {
   "aki": [
    "-",
    "0",
    "0",
    "0",
    "-",
    "-",
    "-"
   ],
   "note": "6ヶ月～2歳"
  }
 }
}