{
 "city": "名古屋市昭和区",
 "asof": "2026-07-01",
 "target": "2026年8月入園分（募集人数）",
 "source": "https://kodomokosodate.city.nagoya.jp/firstuse/boshuwaku.html",
 "legend": "数値=クラス年齢ごとの募集人数。「-」=受入可能年齢でないクラス。「←」=左隣クラスと合わせて募集。受入可能月齢は各施設のnote参照",
 "ages": [
  "産明け",
  "6ヶ月以上",
  "1歳",
  "2歳",
  "3歳",
  "4歳",
  "5歳"
 ],
 "items": {
  "白金保育園": {
   "aki": [
    "2",
    "3",
    "0",
    "0",
    "0",
    "6",
    "7"
   ],
   "note": "産休あけ～5歳"
  },
  "安田保育園": {
   "aki": [
    "-",
    "0",
    "0",
    "0",
    "0",
    "4",
    "5"
   ],
   "note": "6ヶ月～5歳"
  },
  "名広愛児園": {
   "aki": [
    "0",
    "0",
    "0",
    "1",
    "0",
    "0",
    "0"
   ],
   "note": "産休あけ～5歳"
  },
  "駒方保育園": {
   "aki": [
    "0",
    "0",
    "0",
    "0",
    "0",
    "0",
    "0"
   ],
   "note": "産休あけ～5歳"
  },
  "愛厚昭和荘保育園": {
   "aki": [
    "0",
    "0",
    "0",
    "0",
    "0",
    "0",
    "0"
   ],
   "note": "産休あけ～5歳"
  },
  "いりなか保育園": {
   "aki": [
    "0",
    "6",
    "0",
    "1",
    "0",
    "0",
    "0"
   ],
   "note": "産休あけ～5歳 2歳は分園で募集"
  },
  "ひまわり保育園": {
   "aki": [
    "3",
    "←",
    "0",
    "0",
    "0",
    "0",
    "0"
   ],
   "note": "産休あけ～5歳"
  },
  "池内わらべ保育園": {
   "aki": [
    "2",
    "←",
    "0",
    "0",
    "0",
    "0",
    "0"
   ],
   "note": "産休あけ～5歳"
  },
  "やまさと保育園": {
   "aki": [
    "3",
    "←",
    "0",
    "0",
    "0",
    "0",
    "0"
   ],
   "note": "産休あけ～5歳"
  },
  "まこと幼児園": {
   "aki": [
    "-",
    "0",
    "1",
    "1",
    "3",
    "0",
    "0"
   ],
   "note": "11ヶ月～5歳"
  },
  "瑞雲保育園": {
   "aki": [
    "-",
    "0",
    "0",
    "0",
    "0",
    "0",
    "0"
   ],
   "note": "5ヶ月～5歳"
  },
  "松栄保育園": {
   "aki": [
    "-",
    "0",
    "0",
    "0",
    "0",
    "0",
    "0"
   ],
   "note": "6ヶ月～5歳"
  },
  "さくら保育園": {
   "aki": [
    "1",
    "←",
    "0",
    "0",
    "0",
    "0",
    "0"
   ],
   "note": "産休あけ～5歳"
  },
  "たきこ幼児園": {
   "aki": [
    "-",
    "0",
    "0",
    "0",
    "0",
    "0",
    "0"
   ],
   "note": "6ヶ月～5歳"
  },
  "アイン楽園町保育園": {
   "aki": [
    "-",
    "1",
    "0",
    "0",
    "1",
    "0",
    "1"
   ],
   "note": "6ヶ月～5歳"
  },
  "まつかぜ保育園": {
   "aki": [
    "5",
    "←",
    "0",
    "0",
    "0",
    "0",
    "0"
   ],
   "note": "産休あけ～5歳"
  },
  "はな保育園ひろじほんまち": {
   "aki": [
    "0",
    "0",
    "0",
    "0",
    "0",
    "0",
    "0"
   ],
   "note": "産休あけ～5歳"
  },
  "つばめ保育園": {
   "aki": [
    "0",
    "0",
    "0",
    "0",
    "0",
    "0",
    "1"
   ],
   "note": "産休あけ～5歳"
  },
  "キリスト保育園": {
   "aki": [
    "0",
    "1",
    "0",
    "0",
    "0",
    "0",
    "0"
   ],
   "note": "産休あけ～5歳"
  },
  "トット保育園御器所": {
   "aki": [
    "-",
    "0",
    "0",
    "0",
    "0",
    "0",
    "0"
   ],
   "note": "6ヶ月～5歳"
  },
  "アイグラン保育園吹上": {
   "aki": [
    "0",
    "0",
    "1",
    "0",
    "0",
    "0",
    "1"
   ],
   "note": "産休あけ～5歳"
  },
  "鶴舞ちとせ保育園": {
   "aki": [
    "0",
    "0",
    "0",
    "0",
    "0",
    "0",
    "0"
   ],
   "note": "産休あけ～5歳"
  },
  "たきこ第二幼児園にじいろ": {
   "aki": [
    "-",
    "0",
    "0",
    "0",
    "0",
    "0",
    "1"
   ],
   "note": "6ヶ月～5歳"
  },
  "南山ルンビニー園": {
   "aki": [
    "0",
    "0",
    "0",
    "0",
    "0",
    "0",
    "0"
   ],
   "note": "産休あけ～5歳"
  },
  "昭和保育園": {
   "aki": [
    "0",
    "0",
    "0",
    "0",
    "0",
    "0",
    "0"
   ],
   "note": "産休あけ～5歳"
  },
  "もんもの花保育室": {
   "aki": [
    "0",
    "0",
    "0",
    "0",
    "-",
    "-",
    "-"
   ],
   "note": "産休あけ～2歳"
  },
  "小規模保育事業ソラーナいりなか": {
   "aki": [
    "0",
    "2",
    "0",
    "0",
    "-",
    "-",
    "-"
   ],
   "note": "産休あけ～2歳"
  },
  "リーゴ鶴舞": {
   "aki": [
    "0",
    "0",
    "0",
    "0",
    "-",
    "-",
    "-"
   ],
   "note": "産休あけ～2歳"
  },
  "キッズガーデン八事": {
   "aki": [
    "1",
    "←",
    "0",
    "0",
    "-",
    "-",
    "-"
   ],
   "note": "産休あけ～2歳"
  },
  "ほしの子愛児園": {
   "aki": [
    "1",
    "←",
    "0",
    "0",
    "-",
    "-",
    "-"
   ],
   "note": "産休あけ～2歳"
  },
  "スクルドエンジェル保育室ごきそ園": {
   "aki": [
    "0",
    "0",
    "0",
    "0",
    "-",
    "-",
    "-"
   ],
   "note": "産休あけ～2歳"
  },
  "すくすくnursery檀渓通": {
   "aki": [
    "-",
    "0",
    "0",
    "0",
    "-",
    "-",
    "-"
   ],
   "note": "6ヶ月～2歳"
  },
  "ニチイキッズ川名保育室": {
   "aki": [
    "0",
    "0",
    "1",
    "0",
    "-",
    "-",
    "-"
   ],
   "note": "産休あけ～2歳"
  },
  "memorytree保育室滝川園": {
   "aki": [
    "-",
    "0",
    "0",
    "2",
    "-",
    "-",
    "-"
   ],
   "note": "6ヶ月～2歳"
  },
  "いずみ伊勝乳児園": {
   "aki": [
    "0",
    "0",
    "0",
    "0",
    "-",
    "-",
    "-"
   ],
   "note": "産休あけ～2歳"
  },
  "すくすくnursery阿由知通": {
   "aki": [
    "-",
    "0",
    "0",
    "0",
    "-",
    "-",
    "-"
   ],
   "note": "6ヶ月～2歳"
  },
  "memorytree保育室南山園": {
   "aki": [
    "-",
    "0",
    "0",
    "1",
    "-",
    "-",
    "-"
   ],
   "note": "6ヶ月～2歳"
  }
 }
}